linkkt_e2e_handlers/__init__.py
linkkt_e2e_handlers/allocation.py
linkkt_e2e_handlers/exchange.py
linkkt_e2e_handlers/sample_exchange.py
linkkt_e2e_handlers/settings.py
linkkt_e2e_handlers/stoc_gen.py
linkkt_e2e_handlers/trades.py
linkkt_e2e_handlers/user.py
linkkt_e2e_handlers/core/__init__.py
linkkt_e2e_handlers/core/accessor.py
linkkt_e2e_handlers/core/creation.py
linkkt_e2e_handlers/data/__init__.py
linkkt_e2e_handlers/data/stochastic_generator.py
linkkt_e2e_handlers/handlers/__init__.py
linkkt_e2e_handlers/handlers/allocation.py
linkkt_e2e_handlers/handlers/exchange.py
linkkt_e2e_handlers/handlers/org_settings.py
linkkt_e2e_handlers/handlers/requirements.py
linkkt_e2e_handlers/handlers/stoc_gen.py
linkkt_e2e_handlers/handlers/trades.py
linkkt_e2e_handlers/handlers/user.py
linkkt_e2e_handlers/handlers/files/__init__.py
linkkt_e2e_handlers/handlers/files/models/__init__.py
linkkt_e2e_handlers/properties/__init__.py
linkkt_e2e_handlers/properties/abstract.py
linkkt_e2e_handlers/schemas/__init__.py
linkkt_e2e_handlers/stochastic/__init__.py
linkkt_e2e_handlers/stochastic/main.py
linkkt_e2e_handlers/stochastic/generators/__init__.py
linkkt_e2e_handlers/stochastic/generators/cox.py
linkkt_e2e_handlers/stochastic/generators/geometric_brownian.py
linkkt_e2e_handlers/stochastic/generators/heston.py
linkkt_e2e_handlers/stochastic/generators/jump_diffusion.py
linkkt_e2e_handlers/stochastic/generators/ornstien.py
linkkt_e2e_handlers/stochastic/utils/__init__.py
linkkt_e2e_handlers/stochastic/utils/main.py
linkkt_e2e_handlers/stochastic/utils/parameters.py
linkkt_e2e_handlers/utils/__init__.py
linkkt_e2e_handlers/utils/auto.py
linkkt_e2e_handlers/utils/general.py
linkkt_e2e_handlers/utils/manager.py
linkkt_e2e_handlers/utils/ordering.py
linkkt_e2e_handlers/utils/performance.py
linkkt_e2e_handlers/utils/price_generator.py
linkkt_e2e_handlers/utils/tiingo_api.py
linkkt_e2e_handlers/utils/properties/__init__.py
linkkt_e2e_handlers/utils/properties/abstract.py
linkkt_e2e_handlers-0.1.4.dist-info/METADATA
linkkt_e2e_handlers-0.1.4.dist-info/WHEEL
linkkt_e2e_handlers-0.1.4.dist-info/top_level.txt
linkkt_e2e_handlers-0.1.4.dist-info/RECORD
